projnormal/__init__.py
projnormal/param_sampling.py
projnormal/_utils/__init__.py
projnormal/_utils/_linalg.py
projnormal/_utils/_matrix_checks.py
projnormal/classes/__init__.py
projnormal/classes/_optim.py
projnormal/classes/const.py
projnormal/classes/constraints.py
projnormal/classes/ellipse.py
projnormal/classes/ellipse_const.py
projnormal/classes/projected_normal.py
projnormal/formulas/__init__.py
projnormal/formulas/projected_normal/__init__.py
projnormal/formulas/projected_normal/moments.py
projnormal/formulas/projected_normal/probability.py
projnormal/formulas/projected_normal/sampling.py
projnormal/formulas/projected_normal_B/__init__.py
projnormal/formulas/projected_normal_B/moments.py
projnormal/formulas/projected_normal_B/probability.py
projnormal/formulas/projected_normal_B/sampling.py
projnormal/formulas/projected_normal_Bc/__init__.py
projnormal/formulas/projected_normal_Bc/moments.py
projnormal/formulas/projected_normal_Bc/probability.py
projnormal/formulas/projected_normal_Bc/sampling.py
projnormal/formulas/projected_normal_c/__init__.py
projnormal/formulas/projected_normal_c/moments.py
projnormal/formulas/projected_normal_c/probability.py
projnormal/formulas/projected_normal_c/sampling.py
projnormal/formulas/projected_normal_iso/__init__.py
projnormal/formulas/projected_normal_iso/moments.py
projnormal/formulas/projected_normal_iso/probability.py
projnormal/formulas/projected_normal_iso/sampling.py
projnormal/quadratic_forms/__init__.py
projnormal/quadratic_forms/moments.py
projnormal/quadratic_forms/sampling.py
projnormal-0.1.dist-info/METADATA
projnormal-0.1.dist-info/WHEEL
projnormal-0.1.dist-info/licenses/LICENSE
projnormal-0.1.dist-info/RECORD
